pulumi_f5bigip/__init__.py
pulumi_f5bigip/_inputs.py
pulumi_f5bigip/_utilities.py
pulumi_f5bigip/as3.py
pulumi_f5bigip/big_iq_as3.py
pulumi_f5bigip/command.py
pulumi_f5bigip/common_license_manage_big_iq.py
pulumi_f5bigip/do.py
pulumi_f5bigip/event_service_discovery.py
pulumi_f5bigip/fast_application.py
pulumi_f5bigip/fast_http_app.py
pulumi_f5bigip/fast_https_app.py
pulumi_f5bigip/fast_tcp_app.py
pulumi_f5bigip/fast_template.py
pulumi_f5bigip/fast_udp_app.py
pulumi_f5bigip/get_as3_device_information.py
pulumi_f5bigip/ipsec_policy.py
pulumi_f5bigip/ipsec_profile.py
pulumi_f5bigip/net_ike_peer.py
pulumi_f5bigip/net_tunnel.py
pulumi_f5bigip/outputs.py
pulumi_f5bigip/partition.py
pulumi_f5bigip/provider.py
pulumi_f5bigip/pulumi-plugin.json
pulumi_f5bigip/py.typed
pulumi_f5bigip/saas_bot_defense_profile.py
pulumi_f5bigip/ssl_key_cert.py
pulumi_f5bigip/traffic_selector.py
pulumi_f5bigip/waf_policy.py
pulumi_f5bigip/cm/__init__.py
pulumi_f5bigip/cm/_inputs.py
pulumi_f5bigip/cm/device.py
pulumi_f5bigip/cm/device_group.py
pulumi_f5bigip/cm/outputs.py
pulumi_f5bigip/config/__init__.py
pulumi_f5bigip/config/__init__.pyi
pulumi_f5bigip/config/vars.py
pulumi_f5bigip/fast/__init__.py
pulumi_f5bigip/fast/get_aws_service_discovery.py
pulumi_f5bigip/fast/get_azure_service_discovery.py
pulumi_f5bigip/fast/get_consul_service_discovery.py
pulumi_f5bigip/fast/get_gce_service_discovery.py
pulumi_f5bigip/ltm/__init__.py
pulumi_f5bigip/ltm/_inputs.py
pulumi_f5bigip/ltm/cipher_group.py
pulumi_f5bigip/ltm/cipher_rule.py
pulumi_f5bigip/ltm/data_group.py
pulumi_f5bigip/ltm/get_data_group.py
pulumi_f5bigip/ltm/get_irule.py
pulumi_f5bigip/ltm/get_monitor.py
pulumi_f5bigip/ltm/get_node.py
pulumi_f5bigip/ltm/get_policy.py
pulumi_f5bigip/ltm/get_pool.py
pulumi_f5bigip/ltm/i_rule.py
pulumi_f5bigip/ltm/monitor.py
pulumi_f5bigip/ltm/node.py
pulumi_f5bigip/ltm/outputs.py
pulumi_f5bigip/ltm/persistence_profile_cookie.py
pulumi_f5bigip/ltm/persistence_profile_dst_addr.py
pulumi_f5bigip-3.19.1.dist-info/METADATA
pulumi_f5bigip-3.19.1.dist-info/WHEEL
pulumi_f5bigip-3.19.1.dist-info/top_level.txt
pulumi_f5bigip-3.19.1.dist-info/RECORD
